{"version":1530970754,"plugins":[{"defaultBranch":"master","gitId":"KiwiHC16","repository":"Abeille","description":"Abeille pour Jeedom (Gateway ZiGate)","id":"Abeille","name":"Abeille","licence":"AGPL","require":"3.1.7","category":"automation protocol","documentation":"https:\/\/github.com\/KiwiHC16\/Abeille\/blob\/master\/Documentation","changelog":"https:\/\/github.com\/KiwiHC16\/Abeille\/blob\/master\/ChangeLog","author":"kiwihc16","branches":[{"name":"beta","hash":"c3d51b1d9940e63531a4836fa458abee52c296b9"},{"name":"master","hash":"d3c3e0dc79459b433abb84ed526a3290b981e1fe"},{"name":"stable","hash":"672086e6093166850c56a03209d465c09f2b3735"}],"screenshots":[]}]}