{"version":1526541905,"plugins":[{"defaultBranch":"master","gitId":"KiwiHC16","repository":"Abeille","description":"Abeille pour Jeedom (Gateway ZiGate)","id":"Abeille","name":"Abeille","licence":"AGPL","require":"3.1.7","category":"automation protocol","documentation":"https:\/\/github.com\/KiwiHC16\/Abeille\/blob\/master\/Documentation","changelog":"https:\/\/github.com\/KiwiHC16\/Abeille\/blob\/master\/ChangeLog","author":"kiwihc16","branches":[{"name":"beta","hash":"55a0ab27a909bab7748bb92eb51aca2a250f18c5"},{"name":"master","hash":"b93e5c24ba3b5e4a8e0fed2d0e2eea268cd0d491"},{"name":"stable","hash":"4408866b7468c28059b3acee6769d131b668eff0"}],"screenshots":[]}]}